cavityringdown/__init__.py
cavityringdown/loading.py
cavityringdown/ringdown.py
cavityringdown/ringdowns.py
cavityringdown-0.0.8.dist-info/METADATA
cavityringdown-0.0.8.dist-info/WHEEL
cavityringdown-0.0.8.dist-info/licenses/LICENSE
cavityringdown-0.0.8.dist-info/RECORD
