Metadata-Version: 2.3
Name: cavityringdown
Version: 0.0.8
Summary: A package which analyzes cavity transmission ringdown to find the finesse of a cavity
Project-URL: Homepage, https://github.com/kakitkelvinho/cavityringdown
Author-email: Kelvin Ho <kelvin.ho@uibk.ac.at>
Classifier: License :: OSI Approved :: MIT License
Classifier: Operating System :: OS Independent
Requires-Python: >=3.8
